MANIFEST.in
README.rst
setup.cfg
setup.py
docs/HISTORY.txt
docs/INSTALL.txt
docs/LICENSE.GPL
docs/LICENSE.txt
src/collective/__init__.py
src/collective.defaultpage.egg-info/PKG-INFO
src/collective.defaultpage.egg-info/SOURCES.txt
src/collective.defaultpage.egg-info/dependency_links.txt
src/collective.defaultpage.egg-info/entry_points.txt
src/collective.defaultpage.egg-info/namespace_packages.txt
src/collective.defaultpage.egg-info/not-zip-safe
src/collective.defaultpage.egg-info/requires.txt
src/collective.defaultpage.egg-info/top_level.txt
src/collective/defaultpage/__init__.py
src/collective/defaultpage/configure.zcml
src/collective/defaultpage/setuphandlers.py
src/collective/defaultpage/tests.py
src/collective/defaultpage/views.py
src/collective/defaultpage/behaviors/__init__.py
src/collective/defaultpage/behaviors/configure.zcml
src/collective/defaultpage/behaviors/defaultpage_settings.py
src/collective/defaultpage/locales/collective.defaultpage.pot
src/collective/defaultpage/locales/extra.pot
src/collective/defaultpage/locales/de/LC_MESSAGES/collective.defaultpage.po
src/collective/defaultpage/locales/de/LC_MESSAGES/plone.po
src/collective/defaultpage/profiles/default/metadata.xml
src/collective/defaultpage/profiles/default/types/Folder.xml
src/collective/defaultpage/tests/test_behavior_defaultpage_settings.py