Metadata-Version: 2.1
Name: collective.defaultpage
Version: 0.4
Summary: A folder view, which select the first page in a folderwhich the user can access.
Home-page: https://github.com/collective/collective.defaultpage
Author: Maik Derstappen
Author-email: md@derico.de
License: GPL
Keywords: Plone Defaultpage
Platform: UNKNOWN
Classifier: Environment :: Web Environment
Classifier: Framework :: Plone
Classifier: Framework :: Plone :: Addon
Classifier: Framework :: Plone :: 5.1
Classifier: Framework :: Plone :: 5.2
Classifier: Programming Language :: Python
Classifier: Programming Language :: Python :: 2.7
Classifier: Operating System :: OS Independent
Classifier: License :: OSI Approved :: GNU General Public License v2 (GPLv2)
Provides-Extra: test
